Workbook
Name SegmentaciónDeDatos_Categoria: #N/A
Name SegmentaciónDeDatos_Cliente: #N/A
Name SegmentaciónDeDatos_Tipo_Transaccion: #N/A

Sheet Base_De_Datos
A1: Fecha | B1: Mes | C1: ID_Transaccion | D1: Cliente | E1: Tipo_Transaccion | F1: Categoria | G1: Monto_Base | H1: Impuesto | I1: Monto_Total | J1: Banco | K1: Cuenta | L1: Forma_Pago | M1: Estado
A2: 45344 | B2: =TEXT(Tabla1[[#This Row],[Fecha]],"MMMM") -> febrero | C2: TX-100000 | D2: Grupo Soluciones CR | E2: Gasto | F2: Publicidad | G2: 3387 | H2: 0 | I2: =SUM(Tabla1[[#This Row],[Monto_Base]],H2) -> 3387 | J2: Davivienda | K2: Cuenta Corriente | L2: Efectivo | M2: Pagado
A3: 45305 | B3: =TEXT(Tabla1[[#This Row],[Fecha]],"MMMM") -> enero | C3: TX-100001 | D3: Inversiones Atlas | E3: Ingreso | F3: Publicidad | G3: 7605.06 | H3: 988.66 | I3: =SUM(Tabla1[[#This Row],[Monto_Base]],H3) -> 8593.72 | J3: Davivienda | K3: Cuenta Corriente | L3: Efectivo | M3: Pagado
A4: 45373 | B4: =TEXT(Tabla1[[#This Row],[Fecha]],"MMMM") -> marzo | C4: TX-100002 | D4: Laura Salazar | E4: Gasto | F4: Ventas | G4: 11394.17 | H4: 0 | I4: =SUM(Tabla1[[#This Row],[Monto_Base]],H4) -> 11394.17 | J4: Scotiabank | K4: Cuenta Ahorros | L4: Tarjeta Crédito | M4: Pagado
A5: 45475 | B5: =TEXT(Tabla1[[#This Row],[Fecha]],"MMMM") -> julio | C5: TX-100003 | D5: Distribuidora Central | E5: Ingreso | F5: Servicios | G5: 5729.91 | H5: 744.89 | I5: =SUM(Tabla1[[#This Row],[Monto_Base]],H5) -> 6474.8 | J5: Banco de Costa Rica | K5: Tarjeta Crédito Empresarial | L5: Tarjeta Crédito | M5: Pagado
A6: 45442 | B6: =TEXT(Tabla1[[#This Row],[Fecha]],"MMMM") -> mayo | C6: TX-100004 | D6: Fernando Arias | E6: Ingreso | F6: Proveedores | G6: 1228.06 | H6: 159.65 | I6: =SUM(Tabla1[[#This Row],[Monto_Base]],H6) -> 1387.71 | J6: Davivienda | K6: Cuenta Ahorros | L6: Tarjeta Débito | M6: Pagado
A7: 45343 | B7: =TEXT(Tabla1[[#This Row],[Fecha]],"MMMM") -> febrero | C7: TX-100005 | D7: Finanzas del Pacífico | E7: Gasto | F7: Servicios | G7: 12837 | H7: 0 | I7: =SUM(Tabla1[[#This Row],[Monto_Base]],H7) -> 12837 | J7: Scotiabank | K7: Cuenta Ahorros | L7: Efectivo | M7: Pendiente
A8: 45651 | B8: =TEXT(Tabla1[[#This Row],[Fecha]],"MMMM") -> diciembre | C8: TX-100006 | D8: Distribuidora Central | E8: Gasto | F8: Publicidad | G8: 10069.12 | H8: 0 | I8: =SUM(Tabla1[[#This Row],[Monto_Base]],H8) -> 10069.12 | J8: BAC Credomatic | K8: Tarjeta Crédito Empresarial | L8: Tarjeta Débito | M8: Pagado
A9: 45619 | B9: =TEXT(Tabla1[[#This Row],[Fecha]],"MMMM") -> noviembre | C9: TX-100007 | D9: Logística Andina | E9: Gasto | F9: Salarios | G9: 14843.37 | H9: 0 | I9: =SUM(Tabla1[[#This Row],[Monto_Base]],H9) -> 14843.37 | J9: Davivienda | K9: Cuenta Corriente | L9: Tarjeta Crédito | M9: Pagado
A10: 45400 | B10: =TEXT(Tabla1[[#This Row],[Fecha]],"MMMM") -> abril | C10: TX-100008 | D10: Grupo Soluciones CR | E10: Gasto | F10: Proveedores | G10: 4052.73 | H10: 0 | I10: =SUM(Tabla1[[#This Row],[Monto_Base]],H10) -> 4052.73 | J10: Davivienda | K10: Tarjeta Crédito Empresarial | L10: Tarjeta Crédito | M10: Pagado
A11: 45418 | B11: =TEXT(Tabla1[[#This Row],[Fecha]],"MMMM") -> mayo | C11: TX-100009 | D11: Daniel Rojas | E11: Gasto | F11: Alquiler | G11: 4009.96 | H11: 0 | I11: =SUM(Tabla1[[#This Row],[Monto_Base]],H11) -> 4009.96 | J11: Davivienda | K11: Tarjeta Crédito Empresarial | L11: Tarjeta Crédito | M11: Pendiente
A12: 45338 | B12: =TEXT(Tabla1[[#This Row],[Fecha]],"MMMM") -> febrero | C12: TX-100010 | D12: Sofía Vargas | E12: Ingreso | F12: Alquiler | G12: 7667.42 | H12: 996.76 | I12: =SUM(Tabla1[[#This Row],[Monto_Base]],H12) -> 8664.18 | J12: BAC Credomatic | K12: Cuenta Corriente | L12: Tarjeta Débito | M12: Pagado
A13: 45531 | B13: =TEXT(Tabla1[[#This Row],[Fecha]],"MMMM") -> agosto | C13: TX-100011 | D13: Laura Salazar | E13: Ingreso | F13: Proveedores | G13: 5755.21 | H13: 748.18 | I13: =SUM(Tabla1[[#This Row],[Monto_Base]],H13) -> 6503.39 | J13: Davivienda | K13: Cuenta Ahorros | L13: Transferencia | M13: Pagado
... A5001: 45479 | B5001: =TEXT(Tabla1[[#This Row],[Fecha]],"MMMM") -> julio | C5001: TX-104999 | D5001: Daniel Rojas | E5001: Gasto | F5001: Alquiler | G5001: 3912.08 | H5001: 0 | I5001: =SUM(Tabla1[[#This Row],[Monto_Base]],H5001) -> 3912.08 | J5001: Banco de Costa Rica | K5001: Cuenta Ahorros | L5001: Tarjeta Débito | M5001: Pendiente

Sheet Resumen_General
A1: RESUMEN GENERAL
B6: Indicador | C6: Resultado | E6: Descripción
B7: Total Ingresos | C7: =SUMIFS(Base_De_Datos!I:I,Base_De_Datos!E:E,"Ingreso") -> 21301950 | E7: Suma total de ingresos
B8: Total Gastos | C8: =SUMIFS(Base_De_Datos!I:I,Base_De_Datos!E:E,"Gasto") -> 18723381 | E8: Suma total de gastos
B9: Resultado Bruto | C9: =C7-C8 -> 2578569 | E9: Ingresos menos gastos
B10: Total Impuestos | C10: =DSUM(Tabla1[#All],"Impuesto",Base_De_Datos!H:H) -> 2450977.8 | E10: Impuestos totales
B11: Resultado Neto | C11: =C7-C8-C10 -> 127591.15 | E11: Ingresos menos gastos y impuestos
B12: Cantidad Transacciones | C12: =COUNTA(Tabla1[ID_Transaccion]) -> 5000 | E12: Cantidad de transacciones

Sheet Consulta_Transaccion
A1: CONSULTA TRANSACCION
B6: ID_Transaccion | C6: TX-104991
B8: Fecha | C8: Cliente | D8: Tipo_Transaccion | E8: Categoria | F8: Monto_Base | G8: Impuesto
B9: =_xlfn.XLOOKUP(C6,Base_De_Datos!C:C,Base_De_Datos!A:A,"No es posible hayarlo",0) -> 45511 | C9: =_xlfn.XLOOKUP(C6,Base_De_Datos!C:C,Base_De_Datos!D:D,"No es posible hayarlo",0) -> María Fernández | D9: =_xlfn.XLOOKUP(C6,Base_De_Datos!C:C,Base_De_Datos!E:E,"No es posible hayarlo",0) -> Gasto | E9: =_xlfn.XLOOKUP(Consulta_Transaccion!C6,Base_De_Datos!C:C,Base_De_Datos!F:F,"No es posible hayarlo",0) -> Publicidad | F9: =_xlfn.XLOOKUP(C6,Base_De_Datos!C:C,Base_De_Datos!G:G,"No es posible hayarlo",0) -> 6119.91 | G9: =_xlfn.XLOOKUP(C6,Base_De_Datos!C:C,Base_De_Datos!H:H,"No es psoble hayarlo",0) -> 0
B10: Monto_Total | C10: Banco | D10: Cuenta | E10: Forma_Pago | F10: Estado
B11: =_xlfn.XLOOKUP(C6,Base_De_Datos!C:C,Base_De_Datos!I:I,"No es posible hayarlo",0) -> 6119.91 | C11: =_xlfn.XLOOKUP(Consulta_Transaccion!C6,Base_De_Datos!C:C,Base_De_Datos!J:J,"No es posible hayarlo",0) -> BAC Credomatic | D11: =_xlfn.XLOOKUP(C6,Base_De_Datos!C:C,Base_De_Datos!K:K,"No es posible hayarlo",0) -> Cuenta Ahorros | E11: =_xlfn.XLOOKUP(C6,Base_De_Datos!C:C,Base_De_Datos!L:L,"No es posible hayarlo",0) -> Tarjeta Crédito | F11: =_xlfn.XLOOKUP(C6,Base_De_Datos!C:C,Base_De_Datos!M:M,"No es posible hayarlo",0) -> Pendiente

Sheet Análisis
A1: ANÁLISIS
B6: Gasto VS Ingreso | C6: Tipo_Transaccion | G6: Tipo_Transaccion | H6: (Todas)
B7: Mes | C7: Gasto | D7: Ingreso
B8: enero | C8: 1424630.3 | D8: 1791650.4 | G8: Categoria | H8: Gastos por Categoría
B9: febrero | C9: 1505742 | D9: 1747990.2 | G9: Alquiler | H9: 5188059
B10: marzo | C10: 1696372.1 | D10: 1888746.5 | G10: Impuestos | H10: 5210849.1
B11: abril | C11: 1305790.7 | D11: 1517170.7 | G11: Intereses | H11: 5050530.6
B12: mayo | C12: 1653669.1 | D12: 1861806.4 | G12: Proveedores | H12: 5073405.3
B13: junio | C13: 1617925.7 | D13: 1927975.1 | G13: Publicidad | H13: 5048575.3
B14: julio | C14: 1505467.6 | D14: 1813585.6 | G14: Salarios | H14: 4643391.5
B15: agosto | C15: 1805664.9 | D15: 1653344.9 | G15: Servicios | H15: 4941757
B16: septiembre | C16: 1544425.7 | D16: 1819156.1 | G16: Ventas | H16: 4868762.2
B17: octubre | C17: 1538866 | D17: 1735587.9 | G17: Total general | H17: 40025330
B18: noviembre | C18: 1537208.7 | D18: 1792359.7
B19: diciembre | C19: 1587617.6 | D19: 1752575.9 | G19: Tipo_Transaccion | H19: (Todas)
B20: Total general | C20: 18723381 | D20: 21301950
G21: Cliente | H21: Suma de Monto_Total
B22: Banco | C22: Suma de Monto_Total | D22: Cuenta de ID_Transaccion | G22: Daniel Rojas | H22: 2128915.7
B23: BAC Credomatic | C23: 8144817.9 | D23: 1006 | G23: Carlos Mora | H23: 2097324.7
B24: Banco de Costa Rica | C24: 7906082 | D24: 978 | G24: Fernando Arias | H24: 2095642.8
B25: Banco Nacional | C25: 7982788.3 | D25: 974 | G25: Paula Jiménez | H25: 2091232
B26: Davivienda | C26: 7967057.5 | D26: 1022 | G26: Luis Castillo | H26: 2078281.6
B27: Scotiabank | C27: 8024584.5 | D27: 1020 | G27: TechMarket LATAM | H27: 2063733.4
B28: Total general | C28: 40025330 | D28: 5000 | G28: Sofía Vargas | H28: 2056552.2
G29: Constructora Horizonte | H29: 2051448.9
G30: Logística Andina | H30: 2043264.4
G31: Distribuidora Central | H31: 2005973.4
G32: Inversiones Atlas | H32: 2001667.5
G33: Andrea López | H33: 1998309
G34: Comercial Nova S.A. | H34: 1979711.6
G35: Servicios Empresariales Orion | H35: 1955518.1
G36: Grupo Soluciones CR | H36: 1929045
G37: Laura Salazar | H37: 1916407.8
G38: José Hernández | H38: 1908212.4
G39: María Fernández | H39: 1889128.5
G40: Finanzas del Pacífico | H40: 1882380.6
... G42: Total general | H42: 40025330

Sheet Dashboard
A1: DASHBOARD
